linq/__init__.py
linq3-0.3.3.dist-info/METADATA
linq3-0.3.3.dist-info/WHEEL
linq3-0.3.3.dist-info/top_level.txt
linq3-0.3.3.dist-info/RECORD
