Metadata-Version: 2.1
Name: linq3
Version: 0.3.3
Summary: C#-Linq-like wrapper
Home-page: UNKNOWN
Author: weijiang
License: MIT
Platform: UNKNOWN
